MANIFEST.in
README.rst
setup.py
gittar/__init__.py
gittar/sources.py
gittar.egg-info/PKG-INFO
gittar.egg-info/SOURCES.txt
gittar.egg-info/dependency_links.txt
gittar.egg-info/entry_points.txt
gittar.egg-info/requires.txt
gittar.egg-info/top_level.txt