Metadata-Version: 1.1
Name: gittar
Version: 0.6
Summary: The inverse of git archive. Adds a new commit from an archiveor the filesystem.
Home-page: http://github.com/mbr/gittar
Author: Marc Brinkmann
Author-email: git@marcbrinkmann.de
License: MIT
Platform: UNKNOWN
Classifier: Programming Language :: Python :: 2
Classifier: Programming Language :: Python :: 3
